bskydata/__init__.py
bskydata/agents/__init__.py
bskydata/agents/agent.py
bskydata/api/__init__.py
bskydata/api/client.py
bskydata/builders/__init__.py
bskydata/builders/network/search_and_follower_neo4j.py
bskydata/parsers/__init__.py
bskydata/parsers/base.py
bskydata/parsers/profiles/basic.py
bskydata/parsers/search_terms/basic.py
bskydata/scrapers/__init__.py
bskydata/scrapers/followers.py
bskydata/scrapers/follows.py
bskydata/scrapers/profiles.py
bskydata/scrapers/search_terms.py
bskydata/storage/handlers/json.py
bskydata/storage/writers/__init__.py
bskydata/storage/writers/base.py
bskydata/storage/writers/cloud/aws.py
bskydata/storage/writers/cloud/azure.py
bskydata/storage/writers/cloud/base.py
bskydata/storage/writers/cloud/gcp.py
bskydata/storage/writers/database/mongodb.py
bskydata/storage/writers/database/neo4j.py
bskydata/storage/writers/local/local.py
bskydata-0.6.4.dist-info/LICENSE
bskydata-0.6.4.dist-info/METADATA
bskydata-0.6.4.dist-info/WHEEL
bskydata-0.6.4.dist-info/RECORD
