Metadata-Version: 2.1
Name: bskydata
Version: 0.6.4
Summary: 
Home-page: https://github.com/stoltzmaniac/bskydata
License: Apache 2.0
Keywords: bluesky,bsky,api,wrapper,atproto
Author: Scott Stoltzman
Author-email: scottstoltzman@gmail.com
Requires-Python: >=3.11,<3.14
Classifier: License :: Other/Proprietary License
Classifier: Programming Language :: Python :: 3
Classifier: Programming Language :: Python :: 3.11
Classifier: Programming Language :: Python :: 3.12
Classifier: Programming Language :: Python :: 3.13
Requires-Dist: atproto (>=0.0.56,<0.0.57)
Requires-Dist: azure-storage-blob (>=12.24.0,<13.0.0)
Requires-Dist: boto3 (>=1.35.79,<2.0.0)
Requires-Dist: google-cloud-storage (>=2.19.0,<3.0.0)
Requires-Dist: neo4j (>=5.27.0,<6.0.0)
Requires-Dist: pymongo (>=4.10.1,<5.0.0)
Requires-Dist: python-dotenv (>=1.0.1,<2.0.0)
Project-URL: Repository, https://github.com/stoltzmaniac/bskydata
